GenshinUID/__init__.py
GenshinUID/client.py
GenshinUID/models.py
GenshinUID/path.py
GenshinUID/utils.py
nonebot_plugin_genshinuid-4.10.1.dist-info/licenses/LICENSE
nonebot_plugin_genshinuid-4.10.1.dist-info/METADATA
nonebot_plugin_genshinuid-4.10.1.dist-info/WHEEL
nonebot_plugin_genshinuid-4.10.1.dist-info/RECORD
