Metadata-Version: 2.4
Name: nonebot-plugin-genshinuid
Version: 4.10.1
Summary: 支持OneBot(QQ)、OneBotV12、QQ频道、微信、KOOK（开黑啦）、Telegram（电报）、FeiShu（飞书）、DoDo、Villa（米游社大别野）、Discord的全功能NoneBot2原神插件
License: GPL-3.0-or-later
License-File: LICENSE
Author: KimigaiiWuyi
Author-email: 444835641@qq.com
Requires-Python: >=3.8.1,<4
Classifier: License :: OSI Approved :: GNU General Public License v3 or later (GPLv3+)
Classifier: Programming Language :: Python :: 3
Classifier: Programming Language :: Python :: 3.9
Classifier: Programming Language :: Python :: 3.10
Classifier: Programming Language :: Python :: 3.11
Classifier: Programming Language :: Python :: 3.12
Classifier: Programming Language :: Python :: 3.13
Classifier: Programming Language :: Python :: 3.14
Requires-Dist: aiofiles (>=23.1.0)
Requires-Dist: aiohttp (>=3.9.3,<4.0.0)
Requires-Dist: msgspec (>=0.13.1)
Requires-Dist: nonebot-plugin-apscheduler (>=0.2.0)
Requires-Dist: nonebot2 (>=2.0.0b4)
Requires-Dist: pillow (>=9.2.0)
Requires-Dist: websockets (>=11.0.1)
Project-URL: Bug Tracker, https://github.com/KimigaiiWuyi/GenshinUID/issues
Project-URL: Documentation, https://docs.gsuid.gbots.work/#/
Project-URL: Homepage, https://github.com/KimigaiiWuyi/GenshinUID/tree/v4.0-nonebot2
Project-URL: Repository, https://github.com/KimigaiiWuyi/GenshinUID
